vaulboros/api_client.py
vaulboros/helpers.py
vaulboros/vault.py
vaulboros/api/__init__.py
vaulboros/api/approle.py
vaulboros/api/base.py
vaulboros/api/kv.py
vaulboros/api/mount.py
vaulboros/api/token.py
vaulboros-0.1.3.dist-info/METADATA
vaulboros-0.1.3.dist-info/WHEEL
vaulboros-0.1.3.dist-info/RECORD
