Metadata-Version: 2.4
Name: vaulboros
Version: 0.1.3
Summary: High level API library for HashiCorp Vault with sync / async support
Project-URL: Homepage, https://github.com/Seal1998/vaulboros/tree/master
Author-email: Danil Skichko <ayounglad@yandex.ru>
Classifier: License :: OSI Approved :: MIT License
Classifier: Operating System :: OS Independent
Classifier: Programming Language :: Python :: 3
Requires-Python: >=3.8
Requires-Dist: aiohttp==3.9.3
Requires-Dist: requests==2.31.0
